sam_publish/__init__.py
sam_publish/__main__.py
sam_publish/helpers.py
sam_publish/inline_functions.py
sam_publish/move_assets.py
sam_publish/sam_translate.py
sam_publish/tidy_tags_metadata.py
sam_publish-0.2.1.dist-info/LICENSE
sam_publish-0.2.1.dist-info/METADATA
sam_publish-0.2.1.dist-info/WHEEL
sam_publish-0.2.1.dist-info/entry_points.txt
sam_publish-0.2.1.dist-info/top_level.txt
sam_publish-0.2.1.dist-info/RECORD
